cli_tetris-0.1.0.dist-info/licenses/LICENSE
tetris/__init__.py
tetris/cli.py
tetris/const.py
tetris/tetris.py
cli_tetris-0.1.0.dist-info/METADATA
cli_tetris-0.1.0.dist-info/WHEEL
cli_tetris-0.1.0.dist-info/entry_points.txt
cli_tetris-0.1.0.dist-info/top_level.txt
cli_tetris-0.1.0.dist-info/RECORD
