Metadata-Version: 2.4
Name: cli-tetris
Version: 0.1.0
Summary: 俄罗斯方块命令行游戏
Author-email: Allen Shaw <lonsty@sina.com>
License: MIT License
Project-URL: Homepage, https://github.com/lonsty/tetris
Keywords: tetris,game,cli
Requires-Python: >=3.7
License-File: LICENSE
Requires-Dist: typer
Requires-Dist: colorama
Dynamic: license-file
